Metadata-Version: 1.1
Name: policies
Version: 0.4
Summary: An access policy language evaluator.
Home-page: https://github.com/klmitch/policies
Author: Kevin L. Mitchell
Author-email: klmitch@mit.edu
License: GNU General Public License v3 or later (GPLv3+)
Platform: UNKNOWN
Classifier: Development Status :: 5 - Production/Stable
Classifier: Intended Audience :: Developers
Classifier: License :: OSI Approved :: GNU General Public License v3 or later (GPLv3+)
Classifier: Operating System :: OS Independent
Classifier: Programming Language :: Python :: 2.7
Classifier: Programming Language :: Python :: 3.3
Classifier: Topic :: Security
Classifier: Topic :: Software Development :: Interpreters
Classifier: Topic :: Software Development :: Libraries
